LICENSE
MANIFEST.in
README.md
fontreducer.py
setup.py
FontReducer.egg-info/PKG-INFO
FontReducer.egg-info/SOURCES.txt
FontReducer.egg-info/dependency_links.txt
FontReducer.egg-info/top_level.txt
bin/fontreduce