Metadata-Version: 1.1
Name: FontReducer
Version: 0.0.1
Summary: Generate font subsets
Home-page: https://github.com/hachibeeDI/FontReducer
Author: OGURA_Daiki
Author-email: 8hachibee125@gmail.com
License: Copyright 2015 OGURA_Daiki
